drdid/__init__.py
drdid/_version_.py
drdid/drdid.py
drdid/ipwd_did.py
drdid/reg_did.py
drdid/utils.py
drdid-1.1.6.dist-info/licenses/LICENSE
drdid-1.1.6.dist-info/METADATA
drdid-1.1.6.dist-info/WHEEL
drdid-1.1.6.dist-info/top_level.txt
drdid-1.1.6.dist-info/RECORD
